webdriver_test_tools/__init__.py
webdriver_test_tools/test.py
webdriver_test_tools/test_module.py
webdriver_test_tools/classes/__init__.py
webdriver_test_tools/classes/base_page.py
webdriver_test_tools/classes/webdriver_test_case.py
webdriver_test_tools/data/__init__.py
webdriver_test_tools/webdriver/__init__.py
webdriver_test_tools/webdriver/actions/__init__.py
webdriver_test_tools/webdriver/actions/page_actions.py
webdriver_test_tools/webdriver/support/__init__.py
webdriver_test_tools/webdriver/support/expected_conditions.py
webdriver_test_tools-0.1.0.dist-info/DESCRIPTION.rst
webdriver_test_tools-0.1.0.dist-info/METADATA
webdriver_test_tools-0.1.0.dist-info/RECORD
webdriver_test_tools-0.1.0.dist-info/WHEEL
webdriver_test_tools-0.1.0.dist-info/metadata.json
webdriver_test_tools-0.1.0.dist-info/top_level.txt
