Metadata-Version: 2.0
Name: webdriver-test-tools
Version: 0.1.0
Summary: UNKNOWN
Home-page: https://github.com/connordelacruz/webdriver-test-tools
Author: Connor de la Cruz
Author-email: connor.c.delacruz@gmail.com
License: MIT
Download-URL: https://github.com/connordelacruz/webdriver-test-tools/archive/0.1.0.tar.gz
Platform: UNKNOWN
Requires-Dist: selenium (>=3.9)
Requires-Dist: colour-runner (>=0.0.5)
Requires-Dist: randomuser (>=0.1.1)
